<?xml version="1.0" encoding="UTF-8"?>
<objects serializationModel="Studio.02.00.00">
	<object class="AudioFile" id="{4ea0f5df-0b15-4db4-8090-da48c71b82f3}">
		<property name="assetPath">
			<value>IgnasiSongs/ooh ooh.mp3</value>
		</property>
		<property name="isStreaming">
			<value>true</value>
		</property>
		<property name="frequencyInKHz">
			<value>44.0999985</value>
		</property>
		<property name="channelCount">
			<value>2</value>
		</property>
		<property name="length">
			<value>140.06857142857143</value>
		</property>
		<relationship name="masterAssetFolder">
			<destination>{02c4dbd5-9d63-4585-86d4-2d7dda4c31e3}</destination>
		</relationship>
	</object>
</objects>
